ypkgupgr/__init__.py
ypkgupgr/__main__.py
ypkgupgr/altbuf.py
ypkgupgr/appdata.py
ypkgupgr/colors.py
ypkgupgr/consts.py
ypkgupgr/graphics.py
ypkgupgr/ignored.py
ypkgupgr/logs.py
ypkgupgr/misc.py
ypkgupgr-1.14.0.dist-info/licenses/LICENSE
ypkgupgr-1.14.0.dist-info/METADATA
ypkgupgr-1.14.0.dist-info/WHEEL
ypkgupgr-1.14.0.dist-info/entry_points.txt
ypkgupgr-1.14.0.dist-info/top_level.txt
ypkgupgr-1.14.0.dist-info/RECORD
