Metadata-Version: 2.4
Name: ypkgupgr
Version: 1.14.0
Summary: A simple pip package updater
Author-email: yesseruser <yesseruser@gmail.com>
Project-URL: Homepage, https://github.com/yesseruser/ypkgupgr
Project-URL: Bug Tracker, https://github.com/yesseruser/ypkgupgr/issues
Classifier: Programming Language :: Python :: 3
Classifier: License :: OSI Approved :: MIT License
Classifier: Operating System :: OS Independent
Requires-Python: >=3.9
License-File: LICENSE
Requires-Dist: platformdirs<5.0.0
Requires-Dist: click<9.0.0
Requires-Dist: pyperclip<2.0.0
Dynamic: license-file
